paralelocs_qlikapi/__init__.py
paralelocs_qlikapi/__main__.py
paralelocs_qlikapi/cli.py
paralelocs_qlikapi/api/__init__.py
paralelocs_qlikapi/api/api.py
paralelocs_qlikapi/api/auth.py
paralelocs_qlikapi/method/__init__.py
paralelocs_qlikapi/method/app.py
paralelocs_qlikapi/method/base.py
paralelocs_qlikapi/method/reloadtask.py
paralelocs_qlikapi/method/stream.py
paralelocs_qlikapi/method/tag.py
paralelocs_qlikapi/method/task.py
paralelocs_qlikapi-0.2.6.dist-info/AUTHORS.rst
paralelocs_qlikapi-0.2.6.dist-info/LICENSE
paralelocs_qlikapi-0.2.6.dist-info/METADATA
paralelocs_qlikapi-0.2.6.dist-info/WHEEL
paralelocs_qlikapi-0.2.6.dist-info/entry_points.txt
paralelocs_qlikapi-0.2.6.dist-info/top_level.txt
paralelocs_qlikapi-0.2.6.dist-info/RECORD
