Metadata-Version: 2.1
Name: paralelocs-qlikapi
Version: 0.2.6
Summary: Python Library to work with Qlik API
Home-page: https://gitlab.com/paralelo/pyqlikapi/
Author: Paralelo Consultoria e Servicos Ltda
Author-email: contato@paralelocs.com.br
License: Apache-2.0
Project-URL: Changelog, https://paralelo/pyqlikapi/lucasmagalhaes/pyqlikapi/blob/master/CHANGELOG.rst
Project-URL: Issue Tracker, https://paralelo/pyqlikapi/lucasmagalhaes/pyqlikapi/issues
Platform: UNKNOWN
Classifier: Development Status :: 5 - Production/Stable
Classifier: Intended Audience :: Developers
Classifier: License :: OSI Approved :: Apache Software License
Classifier: Operating System :: Unix
Classifier: Operating System :: POSIX
Classifier: Operating System :: Microsoft :: Windows
Classifier: Programming Language :: Python
Classifier: Programming Language :: Python :: 2.7
Classifier: Programming Language :: Python :: 3
Classifier: Programming Language :: Python :: 3.5
Classifier: Programming Language :: Python :: 3.6
Classifier: Programming Language :: Python :: 3.7
Classifier: Programming Language :: Python :: 3.8
Classifier: Programming Language :: Python :: Implementation :: CPython
Classifier: Programming Language :: Python :: Implementation :: PyPy
Classifier: Topic :: Utilities
Requires-Python: >=3.6
Requires-Dist: requests
